devai/__init__.py
devai/__main__.py
devai/cli.py
devai/commands/__init__.py
devai/commands/cmd.py
devai/commands/gitlab.py
devai/commands/jira.py
devai/commands/prompt.py
devai/commands/release.py
devai/commands/review.py
devai/commands/msg/__init__.py
devai/commands/msg/standard.py
devai/commands/msg/streaming.py
devai/util/__init__.py
devai/util/file_processor.py
devai_cli-0.0.0.dist-info/METADATA
devai_cli-0.0.0.dist-info/WHEEL
devai_cli-0.0.0.dist-info/entry_points.txt
devai_cli-0.0.0.dist-info/top_level.txt
devai_cli-0.0.0.dist-info/RECORD
