Metadata-Version: 2.1
Name: devai-cli
Version: 0.0.0
Requires-Dist: click ==8.1.7
Requires-Dist: google-cloud-aiplatform
